Metadata-Version: 2.1
Name: lottie-docs
Version: 1.0
Summary: Python utilities for the lottie docs
Home-page: https://lottiefiles.github.io/lottie-docs/
Author: Mattia Basaglia
Author-email: mattia.basaglia@gmail.com
License: UNKNOWN
Platform: UNKNOWN
